{
	"name": "CreditsScreenLayout",
	"layers": [
		{
			"name": "Layer 0",
			"overriden": 0,
			"subLayers": [],
			"instances": [
				{
					"type": "Text",
					"properties": {
						"text": "********************\n    GAME CREDITS \n********************\n\n--Designers--\nOliver Pison Cortes\nLiam Craven\nLiam Pison Cortes\n\n\n--Programmer--\nOliver Pison Cortes\n\n--Artists--\nLiam Pison Cortes\nLiam Craven\n\n--Producers-\nPex Pison\n",
						"enable-bbcode": true,
						"font": "Roboto",
						"size": 38,
						"line-height": 0,
						"bold": false,
						"italic": false,
						"color": [
							0,
							0,
							0,
							1
						],
						"horizontal-alignment": "center",
						"vertical-alignment": "top",
						"wrapping": "word",
						"initially-visible": true,
						"origin": "top-left"
					},
					"uid": 31,
					"instanceVariables": {},
					"behaviors": {},
					"world": {
						"x": 264,
						"y": 277,
						"width": 548,
						"height": 1129,
						"originX": 0,
						"originY": 0,
						"color": [
							1,
							1,
							1,
							1
						],
						"angle": 0,
						"zElevation": 0
					}
				},
				{
					"type": "ToTitleScreen",
					"properties": {
						"initially-visible": true,
						"initial-animation": "Animation 1",
						"initial-frame": 0,
						"enable-collisions": true,
						"live-preview": false
					},
					"uid": 32,
					"instanceVariables": {},
					"behaviors": {},
					"world": {
						"x": 561,
						"y": 1572,
						"width": 255,
						"height": 260,
						"originX": 0.5,
						"originY": 0.5,
						"color": [
							1,
							1,
							1,
							1
						],
						"angle": 0,
						"zElevation": 0
					}
				}
			],
			"sid": 195388934264631,
			"effectTypes": [],
			"isInitiallyVisible": true,
			"isInitiallyInteractive": true,
			"color": [
				1,
				1,
				1,
				1
			],
			"backgroundColor": [
				1,
				1,
				1,
				1
			],
			"isTransparent": false,
			"parallaxX": 1,
			"parallaxY": 1,
			"scaleRate": 1,
			"forceOwnTexture": false,
			"renderingMode": "3d",
			"drawOrder": "z-order",
			"useRenderCells": false,
			"blendMode": "normal",
			"zElevation": 0,
			"global": false
		}
	],
	"sid": 838988895345718,
	"nonworld-instances": [],
	"effectTypes": [],
	"width": 2160,
	"height": 3840,
	"unboundedScrolling": false,
	"vpX": 0.5,
	"vpY": 0.5,
	"projection": "perspective",
	"eventSheet": "CreditsScreenEvents"
}